aiomobilevikings/__init__.py
aiomobilevikings/client.py
aiomobilevikings/const.py
aiomobilevikings-0.3.0.dist-info/LICENSE
aiomobilevikings-0.3.0.dist-info/METADATA
aiomobilevikings-0.3.0.dist-info/WHEEL
aiomobilevikings-0.3.0.dist-info/top_level.txt
aiomobilevikings-0.3.0.dist-info/RECORD
