Metadata-Version: 2.1
Name: aiomobilevikings
Version: 0.3.0
Summary: Module to communicate to the Mobile Vikings API
Home-page: https://github.com/geertmeersman/aiomobilevikings
Author: Geert Meersman
Author-email: geertmeersman@gmail.com
License: MIT
Classifier: Programming Language :: Python :: 3
Classifier: License :: OSI Approved :: Apache Software License
Classifier: Operating System :: OS Independent
License-File: LICENSE
Requires-Dist: aiohttp
Requires-Dist: pip<24.4,>=8.0.3
Requires-Dist: ruff==0.8.2
